MANIFEST.in
licence.txt
setup.py
gayathripack/__init__.py
gayathripack.egg-info/PKG-INFO
gayathripack.egg-info/SOURCES.txt
gayathripack.egg-info/dependency_links.txt
gayathripack.egg-info/top_level.txt