Metadata-Version: 2.1
Name: gayathripack
Version: 0.0.1
Summary: this is a trial package used for calculation.
Home-page: UNKNOWN
Author: Gayathri Sunil
Author-email: gayathrisachusunil@gmail.com
License: MIT
Platform: UNKNOWN
License-File: licence.txt
